<?xml version="1.0" encoding="UTF-8"?>
<persistence version="2.2" xmlns="http://xmlns.jcp.org/xml/ns/persistence" xmlns:xsi="http://www.w3.org/2001/XMLSchema-instance" xsi:schemaLocation="http://xmlns.jcp.org/xml/ns/persistence http://xmlns.jcp.org/xml/ns/persistence/persistence_2_2.xsd">
	<persistence-unit name="TPJPA">
		<provider>org.hibernate.jpa.HibernatePersistenceProvider</provider>
		<class>ept.dic2.tpjpa.entities.Categorie</class>
		<class>ept.dic2.tpjpa.entities.Marque</class>
		<class>ept.dic2.tpjpa.entities.Produit</class>
		<class>ept.dic2.tpjpa.entities.Stock</class>
		<class>ept.dic2.tpjpa.entities.StockPK</class>
		
		<properties>
			<property name="javax.persistence.jdbc.driver" value="com.mysql.jdbc.Driver"/>
			<property name="javax.persistence.jdbc.url" value="jdbc:mysql://localhost:3306/production"/>
			<property name="javax.persistence.jdbc.user" value="guUser"/>
			<property name="javax.persistence.jdbc.password" value="guUser"/>
		</properties>
	</persistence-unit>
</persistence>
